wesley/__init__.py
wesley/__main__.py
wesley/cli.py
wesley-0.1.0.dist-info/METADATA
wesley-0.1.0.dist-info/WHEEL
wesley-0.1.0.dist-info/entry_points.txt
wesley-0.1.0.dist-info/RECORD
